[
  {
    "source": "Autoscout24",
    "source_id": "autoscout24_nas",
    "fiabilite_source": 6,
    "titre": "BMW Série 3 PHEV Touring ? · 18 822 km",
    "vendeur": "Pro AS24",
    "url": "https://www.autoscout24.fr/offres/bmw-330-serie-touring-g21-330e-xdrive-292-ch-bva8-m-sport-electrique-essence-noir-15bfb2b4-4d84-4efb-aa40-bee3353f34f5",
    "prix": 39980,
    "annee": null,
    "km": 18822,
    "toit_ouvrant": null,
    "garantie_mois": null,
    "premiere_main": false,
    "entretien_constructeur": null,
    "modele_id": "bmw_3series",
    "modele_nom": "BMW Série 3 PHEV Touring",
    "score_total": 0.7,
    "score_detail": {
      "annee": 60.0,
      "kilometrage": 100.0,
      "prix_vs_marche": 70.0,
      "garantie": 40.0,
      "equipements_cles": 40.0,
      "fiabilite_source": 60.0
    },
    "cote_reference": 41000,
    "niveau_alerte": "FAIBLE",
    "emoji_alerte": "⚪",
    "recommandation": "✅ Kilométrage excellent (18 822 km) · ⚠️ Toit ouvrant / panoramique : à confirmer · ⚠️ Garantie : à vérifier auprès du vendeur · ℹ️ Données à compléter : année",
    "score_date": "2026-05-14T07:45:20.244354",
    "id": "6531f21ad4e4",
    "derniere_vue": "2026-05-14T07:45:20.265416",
    "premiere_vue": "2026-05-12T11:30:20.039791",
    "first_seen_at": "2026-05-12T11:30:20.039791",
    "est_nouvelle": false
  },
  {
    "source": "Autoscout24",
    "source_id": "autoscout24_nas",
    "fiabilite_source": 6,
    "titre": "BMW Série 3 PHEV Touring ? · 42 600 km",
    "vendeur": "Pro AS24",
    "url": "https://www.autoscout24.fr/offres/bmw-320-touring-320eas-phev-pack-m-cuir-camera-att-rem-electrique-essence-noir-764b9a53-946d-43b2-87af-446136100fe0",
    "prix": 37490,
    "annee": null,
    "km": 42600,
    "toit_ouvrant": null,
    "garantie_mois": null,
    "premiere_main": false,
    "entretien_constructeur": null,
    "modele_id": "bmw_3series",
    "modele_nom": "BMW Série 3 PHEV Touring",
    "score_total": 0.6,
    "score_detail": {
      "annee": 60.0,
      "kilometrage": 75.0,
      "prix_vs_marche": 85.0,
      "garantie": 40.0,
      "equipements_cles": 40.0,
      "fiabilite_source": 60.0
    },
    "cote_reference": 41000,
    "niveau_alerte": "FAIBLE",
    "emoji_alerte": "⚪",
    "recommandation": "✅ Prix sous la cote — opportunité · ⚠️ Toit ouvrant / panoramique : à confirmer · ⚠️ Garantie : à vérifier auprès du vendeur · ℹ️ Données à compléter : année",
    "score_date": "2026-05-14T07:45:20.244081",
    "id": "77ffda143320",
    "derniere_vue": "2026-05-14T07:45:20.265416",
    "premiere_vue": "2026-05-12T11:30:20.039791",
    "first_seen_at": "2026-05-12T11:30:20.039791",
    "est_nouvelle": false
  },
  {
    "source": "Autoscout24",
    "source_id": "autoscout24_nas",
    "fiabilite_source": 6,
    "titre": "BMW Série 3 PHEV Touring ? · 47 217 km",
    "vendeur": "Pro AS24",
    "url": "https://www.autoscout24.fr/offres/bmw-320-320ea-204ch-m-sport-electrique-essence-5d3cd139-f024-4890-9e0a-683d055308e4",
    "prix": 37799,
    "annee": null,
    "km": 47217,
    "toit_ouvrant": null,
    "garantie_mois": null,
    "premiere_main": false,
    "entretien_constructeur": null,
    "modele_id": "bmw_3series",
    "modele_nom": "BMW Série 3 PHEV Touring",
    "score_total": 0.6,
    "score_detail": {
      "annee": 60.0,
      "kilometrage": 75.0,
      "prix_vs_marche": 85.0,
      "garantie": 40.0,
      "equipements_cles": 40.0,
      "fiabilite_source": 60.0
    },
    "cote_reference": 41000,
    "niveau_alerte": "FAIBLE",
    "emoji_alerte": "⚪",
    "recommandation": "✅ Prix sous la cote — opportunité · ⚠️ Toit ouvrant / panoramique : à confirmer · ⚠️ Garantie : à vérifier auprès du vendeur · ℹ️ Données à compléter : année",
    "score_date": "2026-05-14T07:45:20.244148",
    "id": "1c96532211f6",
    "derniere_vue": "2026-05-14T07:45:20.265416",
    "premiere_vue": "2026-05-12T11:30:20.039791",
    "first_seen_at": "2026-05-12T11:30:20.039791",
    "est_nouvelle": false
  },
  {
    "source": "Autoscout24",
    "source_id": "autoscout24_nas",
    "fiabilite_source": 6,
    "titre": "BMW Série 3 PHEV Touring ? · 38 965 km",
    "vendeur": "Pro AS24",
    "url": "https://www.autoscout24.fr/offres/bmw-320-320e-touring-m-sport-toit-ouvrant-pack-evasion-pack-confort-electrique-essence-noir-23b52e01-e7de-4344-941b-51e043857eca",
    "prix": 38990,
    "annee": null,
    "km": 38965,
    "toit_ouvrant": true,
    "garantie_mois": null,
    "premiere_main": false,
    "entretien_constructeur": null,
    "modele_id": "bmw_3series",
    "modele_nom": "BMW Série 3 PHEV Touring",
    "score_total": 0.6,
    "score_detail": {
      "annee": 60.0,
      "kilometrage": 75.0,
      "prix_vs_marche": 70.0,
      "garantie": 40.0,
      "equipements_cles": 76.0,
      "fiabilite_source": 60.0
    },
    "cote_reference": 41000,
    "niveau_alerte": "FAIBLE",
    "emoji_alerte": "⚪",
    "recommandation": "✅ Toit ouvrant / panoramique confirmé · ⚠️ Garantie : à vérifier auprès du vendeur · ℹ️ Données à compléter : année",
    "score_date": "2026-05-14T07:45:20.244213",
    "id": "0c8bd1084c98",
    "derniere_vue": "2026-05-14T07:45:20.265416",
    "premiere_vue": "2026-05-12T11:30:20.039791",
    "first_seen_at": "2026-05-12T11:30:20.039791",
    "est_nouvelle": false
  },
  {
    "source": "Autoscout24",
    "source_id": "autoscout24_nas",
    "fiabilite_source": 6,
    "titre": "BMW Série 3 PHEV Touring ? · 33 746 km",
    "vendeur": "Pro AS24",
    "url": "https://www.autoscout24.fr/offres/bmw-320-320ea-204ch-m-sport-electrique-essence-f1b6cbdf-1434-434a-ba98-aae900ee94c1",
    "prix": 39699,
    "annee": null,
    "km": 33746,
    "toit_ouvrant": null,
    "garantie_mois": null,
    "premiere_main": false,
    "entretien_constructeur": null,
    "modele_id": "bmw_3series",
    "modele_nom": "BMW Série 3 PHEV Touring",
    "score_total": 0.6,
    "score_detail": {
      "annee": 60.0,
      "kilometrage": 75.0,
      "prix_vs_marche": 70.0,
      "garantie": 40.0,
      "equipements_cles": 40.0,
      "fiabilite_source": 60.0
    },
    "cote_reference": 41000,
    "niveau_alerte": "FAIBLE",
    "emoji_alerte": "⚪",
    "recommandation": "⚠️ Toit ouvrant / panoramique : à confirmer · ⚠️ Garantie : à vérifier auprès du vendeur · ℹ️ Données à compléter : année",
    "score_date": "2026-05-14T07:45:20.244277",
    "id": "a75ed5e0969d",
    "derniere_vue": "2026-05-14T07:45:20.265416",
    "premiere_vue": "2026-05-12T11:30:20.039791",
    "first_seen_at": "2026-05-12T11:30:20.039791",
    "est_nouvelle": false
  },
  {
    "source": "Autoscout24",
    "source_id": "autoscout24_nas",
    "fiabilite_source": 6,
    "titre": "BMW Série 3 PHEV Touring ? · 21 700 km",
    "vendeur": "Pro AS24",
    "url": "https://www.autoscout24.fr/offres/bmw-330-g21-330e-292ch-m-sport-loa-599-euros-sans-apport-electrique-essence-blanc-361dd519-6f37-4fc9-9009-b97831a0197b",
    "prix": 40990,
    "annee": null,
    "km": 21700,
    "toit_ouvrant": null,
    "garantie_mois": null,
    "premiere_main": false,
    "entretien_constructeur": null,
    "modele_id": "bmw_3series",
    "modele_nom": "BMW Série 3 PHEV Touring",
    "score_total": 0.6,
    "score_detail": {
      "annee": 60.0,
      "kilometrage": 90.0,
      "prix_vs_marche": 50.0,
      "garantie": 40.0,
      "equipements_cles": 40.0,
      "fiabilite_source": 60.0
    },
    "cote_reference": 41000,
    "niveau_alerte": "FAIBLE",
    "emoji_alerte": "⚪",
    "recommandation": "✅ Kilométrage excellent (21 700 km) · ⚠️ Toit ouvrant / panoramique : à confirmer · ⚠️ Garantie : à vérifier auprès du vendeur · ℹ️ Données à compléter : année",
    "score_date": "2026-05-14T07:45:20.244436",
    "id": "63f428bc0ecb",
    "derniere_vue": "2026-05-14T07:45:20.265416",
    "premiere_vue": "2026-05-13T07:30:16.139144",
    "first_seen_at": "2026-05-13T07:30:16.139144",
    "est_nouvelle": false
  },
  {
    "source": "Autoscout24",
    "source_id": "autoscout24_nas",
    "fiabilite_source": 6,
    "titre": "BMW Série 3 PHEV Touring ? · 38 578 km",
    "vendeur": "Pro AS24",
    "url": "https://www.autoscout24.fr/offres/bmw-320-320ea-204ch-m-sport-electrique-essence-ea59be17-e245-425d-9d1c-df20a27b390d",
    "prix": 40999,
    "annee": null,
    "km": 38578,
    "toit_ouvrant": null,
    "garantie_mois": null,
    "premiere_main": false,
    "entretien_constructeur": null,
    "modele_id": "bmw_3series",
    "modele_nom": "BMW Série 3 PHEV Touring",
    "score_total": 0.6,
    "score_detail": {
      "annee": 60.0,
      "kilometrage": 75.0,
      "prix_vs_marche": 50.0,
      "garantie": 40.0,
      "equipements_cles": 40.0,
      "fiabilite_source": 60.0
    },
    "cote_reference": 41000,
    "niveau_alerte": "FAIBLE",
    "emoji_alerte": "⚪",
    "recommandation": "⚠️ Toit ouvrant / panoramique : à confirmer · ⚠️ Garantie : à vérifier auprès du vendeur · ℹ️ Données à compléter : année",
    "score_date": "2026-05-14T07:45:20.244501",
    "id": "714ee44a2494",
    "derniere_vue": "2026-05-14T07:45:20.265416",
    "premiere_vue": "2026-05-12T11:30:20.039791",
    "first_seen_at": "2026-05-12T11:30:20.039791",
    "est_nouvelle": false
  }
]